StochasticProcessSimulator/StochasticProcessSimulator.py
StochasticProcessSimulator/__init__.py
StochasticProcessSimulator-0.1.3.dist-info/LICENSE.txt
StochasticProcessSimulator-0.1.3.dist-info/METADATA
StochasticProcessSimulator-0.1.3.dist-info/WHEEL
StochasticProcessSimulator-0.1.3.dist-info/top_level.txt
StochasticProcessSimulator-0.1.3.dist-info/RECORD
