Metadata-Version: 2.1
Name: StochasticProcessSimulator
Version: 0.1.3
Summary: A package for simulating and plotting stochastic processes using discretization of SDEs.
Home-page: https://github.com/Boris-73-TA/SDEs
Author: Boris Ter-Avanesov
Author-email: bt2522@columbia.edu
Classifier: Programming Language :: Python :: 3
Classifier: License :: OSI Approved :: MIT License
Classifier: Operating System :: OS Independent
Requires-Python: >=3.8
License-File: LICENSE.txt
Requires-Dist: numpy
Requires-Dist: scipy
Requires-Dist: statsmodels
Requires-Dist: matplotlib
Requires-Dist: pandas
